HDPython/HDPython_AST.py
HDPython/__init__.py
HDPython/base.py
HDPython/base_helpers.py
HDPython/core_pack_generator.py
HDPython/debug_vis.py
HDPython/free_type_helper.py
HDPython/global_settings.py
HDPython/hdl_converter.py
HDPython/lib_enums.py
HDPython/master_slave.py
HDPython/object_factory.py
HDPython/object_name_maker.py
HDPython/primitive_type_converter.py
HDPython/simulation.py
HDPython/slice_base.py
HDPython/test_handler.py
HDPython/to_v_object.py
HDPython/type_info.py
HDPython/type_queries.py
HDPython/v_Package.py
HDPython/v_class.py
HDPython/v_class_handle.py
HDPython/v_class_trans.py
HDPython/v_entity.py
HDPython/v_entity_gsystem.py
HDPython/v_entity_list.py
HDPython/v_enum.py
HDPython/v_function.py
HDPython/v_list.py
HDPython/v_record.py
HDPython/v_symbol.py
HDPython/ast/AST_Classes.py
HDPython/ast/AST_FreeFunction.py
HDPython/ast/AST_MemFunctionCalls.py
HDPython/ast/AST_entity_converter.py
HDPython/ast/AST_member_function_converter.py
HDPython/ast/__init__.py
HDPython/ast/ast_hdl_error.py
HDPython/ast/ast_classes/__init__.py
HDPython/ast/ast_classes/ast_Attribute.py
HDPython/ast/ast_classes/ast_FunctionDef.py
HDPython/ast/ast_classes/ast_Num.py
HDPython/ast/ast_classes/ast_assignment.py
HDPython/ast/ast_classes/ast_base.py
HDPython/ast/ast_classes/ast_break.py
HDPython/ast/ast_classes/ast_compare.py
HDPython/ast/ast_classes/ast_constant.py
HDPython/ast/ast_classes/ast_continue.py
HDPython/ast/ast_classes/ast_expr.py
HDPython/ast/ast_classes/ast_for.py
HDPython/ast/ast_classes/ast_function_architeture.py
HDPython/ast/ast_classes/ast_function_call.py
HDPython/ast/ast_classes/ast_function_porcess_combinational.py
HDPython/ast/ast_classes/ast_function_porcess_timed.py
HDPython/ast/ast_classes/ast_function_process.py
HDPython/ast/ast_classes/ast_function_process_body.py
HDPython/ast/ast_classes/ast_if.py
HDPython/ast/ast_classes/ast_list.py
HDPython/ast/ast_classes/ast_name.py
HDPython/ast/ast_classes/ast_named_constant.py
HDPython-0.0.5.dist-info/LICENSE.txt
HDPython-0.0.5.dist-info/METADATA
HDPython-0.0.5.dist-info/WHEEL
HDPython-0.0.5.dist-info/top_level.txt
HDPython-0.0.5.dist-info/RECORD
