Metadata-Version: 2.1
Name: HDPython
Version: 0.0.5
Summary: High Level Object Oriented Hardware Description Library
Home-page: https://github.com/HardwareDesignWithPython/HDPython
Author: Richard Peschke
Author-email: rp40@hawaii.edu
License: UNKNOWN
Platform: UNKNOWN
Classifier: Programming Language :: Python :: 3
Classifier: License :: OSI Approved :: MIT License
Classifier: Operating System :: OS Independent
Requires-Python: >=3.8
Requires-Dist: pyvcd
